mongo_unit_of_work/__init__.py
mongo_unit_of_work/abstraction.py
mongo_unit_of_work/unit_of_work_tools.py
mongo_unit_of_work-0.1.0.dist-info/WHEEL
mongo_unit_of_work-0.1.0.dist-info/METADATA
mongo_unit_of_work-0.1.0.dist-info/RECORD
